notementum/__init__.py
notementum/__main__.py
notementum/highlight_style.py
notementum/markdown.py
notementum/model.py
notementum/view_controller.py
notementum/res/notes.ui
notementum/res/notes.ui~
notementum/res/preview.html
notementum/views/__init__.py
notementum/views/dialog_about.py
notementum/views/dialog_assign_notebook.py
notementum/views/dialog_attachments.py
notementum/views/dialog_delete_attachment.py
notementum/views/dialog_delete_note.py
notementum/views/main_window.py
notementum/views/notebook_list.py
notementum/views/notes_list.py
notementum/views/source_editor.py
notementum-0.1.0.dist-info/LICENSE
notementum-0.1.0.dist-info/METADATA
notementum-0.1.0.dist-info/WHEEL
notementum-0.1.0.dist-info/entry_points.txt
notementum-0.1.0.dist-info/top_level.txt
notementum-0.1.0.dist-info/RECORD
