Metadata-Version: 2.1
Name: notementum
Version: 0.1.0
Summary: A native Markdown notebook app.
Home-page: UNKNOWN
Author: Ivan Fonseca
Author-email: ivanfon@riseup.net
License: GPLv3+
Keywords: markdown
Platform: UNKNOWN
Classifier: Development Status :: 3 - Alpha
Classifier: Environment :: X11 Applications :: GTK
Classifier: Intended Audience :: End Users/Desktop
Classifier: License :: OSI Approved :: GNU General Public License v3 or later (GPLv3+)
Classifier: Natural Language :: English
Classifier: Operating System :: POSIX
Classifier: Programming Language :: Python :: 3 :: Only
Classifier: Programming Language :: Python :: 3.5
Classifier: Programming Language :: Python :: 3.6
Classifier: Programming Language :: Python :: 3.7
Classifier: Programming Language :: Python :: 3.8
Classifier: Topic :: Text Editors
Classifier: Topic :: Utilities
Requires-Dist: PyGObject
Requires-Dist: mistletoe
Requires-Dist: pygments
